<?xml version="1.0" encoding="utf-8"?>
<resources xmlns:xliff="urn:oasis:names:tc:xliff:document:1.2">
    <plurals name="emailleak_breach_accounts_count_plural">
        <item quantity="one"><xliff:g id="number" example="1">%1$s</xliff:g> compte</item>
        <item quantity="other"><xliff:g id="number">%1$s</xliff:g> comptes</item>
    </plurals>
    <plurals name="passwordleak_occurrences_count_plural">
        <item quantity="one"><xliff:g id="number" example="1">%1$s</xliff:g> ocurrència</item>
        <item quantity="other"><xliff:g id="number">%1$s</xliff:g> ocurrències</item>
    </plurals>
    <plurals name="word_count_plural">
        <item quantity="one"><xliff:g id="number" example="1">%1$s</xliff:g> paraula</item>
        <item quantity="other"><xliff:g id="number">%1$s</xliff:g> paraules</item>
    </plurals>
    <plurals name="result_count_plural">
        <item quantity="one"><xliff:g id="number" example="1">%1$s</xliff:g> resultat</item>
        <item quantity="other"><xliff:g id="number">%1$s</xliff:g> resultats</item>
    </plurals>
    <plurals name="seconds_plural">
        <item quantity="one"><xliff:g id="number" example="1">%1$s</xliff:g> segon</item>
        <item quantity="other"><xliff:g id="number">%1$s</xliff:g> segons</item>
    </plurals>
    <plurals name="minutes_plural">
        <item quantity="one"><xliff:g id="number" example="1">%1$s</xliff:g> minut</item>
        <item quantity="other"><xliff:g id="number">%1$s</xliff:g> minuts</item>
    </plurals>
    <plurals name="hours_plural">
        <item quantity="one"><xliff:g id="number" example="1">%1$s</xliff:g> hora</item>
        <item quantity="other"><xliff:g id="number">%1$s</xliff:g> hores</item>
    </plurals>
    <plurals name="days_plural">
        <item quantity="one"><xliff:g id="number" example="1">%1$s</xliff:g> dia</item>
        <item quantity="other"><xliff:g id="number">%1$s</xliff:g> dies</item>
    </plurals>
</resources>
